insightsGG/App.py
insightsGG/Networking.py
insightsGG/__init__.py
insightsGG/Errors/LoginError.py
insightsGG/Errors/VideoError.py
insightsGG/Errors/__init__.py
insightsGG/Objects/Me.py
insightsGG/Objects/Role.py
insightsGG/Objects/Tag.py
insightsGG/Objects/Team.py
insightsGG/Objects/User.py
insightsGG/Objects/Video.py
insightsGG/Objects/__init__.py
insightsGG/Objects/OverwatchAnalytics/Event.py
insightsGG/Objects/OverwatchAnalytics/FirstEvent.py
insightsGG/Objects/OverwatchAnalytics/Kill.py
insightsGG/Objects/OverwatchAnalytics/Match.py
insightsGG/Objects/OverwatchAnalytics/Player.py
insightsGG/Objects/OverwatchAnalytics/Score.py
insightsGG/Objects/OverwatchAnalytics/TeamFight.py
insightsGG/Objects/OverwatchAnalytics/Ult.py
insightsGG/Objects/OverwatchAnalytics/__init__.py
InsightsGG-0.9.2.dist-info/METADATA
InsightsGG-0.9.2.dist-info/WHEEL
InsightsGG-0.9.2.dist-info/top_level.txt
InsightsGG-0.9.2.dist-info/RECORD
