Metadata-Version: 2.1
Name: InsightsGG
Version: 0.9.2
Summary: The unofficial api for Insights.gg
Home-page: https://github.com/thoward02/InsightsGG
Author: Aud
Author-email: audaciousxth@gmail.com
License: UNKNOWN
Platform: UNKNOWN
Classifier: Programming Language :: Python :: 3
Classifier: License :: OSI Approved :: MIT License
Classifier: Operating System :: OS Independent
Requires-Python: >=3.5
Requires-Dist: requests
